{
    "Ar36": {
        "error": 0.0004909106547759357,
        "error_type": "SEM",
        "filter_outliers_dict": {
            "filter_outliers": false,
            "iterations": 1,
            "std_devs": 2,
            "use_iqr_filtering": false,
            "use_standard_deviation_filtering": false
        },
        "fit": "Linear",
        "fn": 150,
        "include_baseline_error": false,
        "n": 150,
        "outlier_excluded": [],
        "reviewed": true,
        "user_excluded": [],
        "value": 0.03786972838849641
    },
    "Ar37": {
        "error": 0.010883582677823724,
        "error_type": "SEM",
        "filter_outliers_dict": {
            "filter_outliers": true,
            "iterations": 1,
            "std_devs": 2
        },
        "fit": "Linear",
        "value": 4.031780038335885
    },
    "Ar38": {
        "error": 0.011261880961021173,
        "error_type": "SEM",
        "filter_outliers_dict": {
            "filter_outliers": false,
            "iterations": 0,
            "std_devs": 0,
            "use_iqr_filtering": false,
            "use_standard_deviation_filtering": false
        },
        "fit": "Linear",
        "fn": 150,
        "include_baseline_error": false,
        "n": 150,
        "outlier_excluded": [],
        "reviewed": true,
        "user_excluded": [],
        "value": 0.14945206795424293
    },
    "Ar39": {
        "error": 0.010747336824254047,
        "error_type": "SEM",
        "filter_outliers_dict": {
            "filter_outliers": false,
            "iterations": 0,
            "std_devs": 0,
            "use_iqr_filtering": false,
            "use_standard_deviation_filtering": false
        },
        "fit": "Linear",
        "fn": 150,
        "include_baseline_error": false,
        "n": 150,
        "outlier_excluded": [],
        "reviewed": true,
        "user_excluded": [],
        "value": 4.825222815029617
    },
    "Ar40": {
        "error": 0.0756586427814232,
        "error_type": "SEM",
        "filter_outliers_dict": {
            "filter_outliers": false,
            "iterations": 0,
            "std_devs": 0,
            "use_iqr_filtering": false,
            "use_standard_deviation_filtering": false
        },
        "fit": "Linear",
        "fn": 150,
        "include_baseline_error": false,
        "n": 150,
        "outlier_excluded": [],
        "reviewed": true,
        "user_excluded": [],
        "value": 878.3335160770281
    }
}